LICENSE.txt
README
distribute_setup.py
setup.cfg
setup.py
doc/History
multidrizzle/__init__.py
multidrizzle/acs_input.py
multidrizzle/deriv.py
multidrizzle/driz_cr.py
multidrizzle/input_image.py
multidrizzle/manager.py
multidrizzle/mdrizpars.py
multidrizzle/mdzhandler.py
multidrizzle/minmed.py
multidrizzle/nicmos_input.py
multidrizzle/procstep.py
multidrizzle/quickDeriv.py
multidrizzle/static_mask.py
multidrizzle/stis_input.py
multidrizzle/utilities.py
multidrizzle/version.py
multidrizzle/wfc3_input.py
multidrizzle/wfpc2_input.py
multidrizzle.egg-info/PKG-INFO
multidrizzle.egg-info/SOURCES.txt
multidrizzle.egg-info/dependency_links.txt
multidrizzle.egg-info/not-zip-safe
multidrizzle.egg-info/requires.txt
multidrizzle.egg-info/top_level.txt