Metadata-Version: 1.1
Name: multidrizzle
Version: 3.4.2
Summary: UNKNOWN
Home-page: http://www.stsci.edu/resources/software_hardware/stsci_python
Author: Warren Hack, Christopher Hanley, Ivo Busko, Robert Jedrzejewski, Anton Koekemoer
Author-email: help@stsci.edu
License: UNKNOWN
Platform: UNKNOWN
Classifier: Intended Audience :: Science/Research
Classifier: License :: OSI Approved :: BSD License
Classifier: Operating System :: OS Independent
Classifier: Programming Language :: Python
Classifier: Topic :: Scientific/Engineering :: Astronomy
Classifier: Topic :: Software Development :: Libraries :: Python Modules
